sanctum/__init__.py
sanctum/auth.py
sanctum/client.py
sanctum/exceptions.py
sanctum/info.py
sanctum/rbac.py
sanctum/tokens.py
sanctum/user.py
sanctum-0.1.1.dist-info/LICENSE
sanctum-0.1.1.dist-info/METADATA
sanctum-0.1.1.dist-info/WHEEL
sanctum-0.1.1.dist-info/RECORD
