Metadata-Version: 2.1
Name: sanctum
Version: 0.1.1
Summary: Developer-friendly AWS Cognito client for Python, with clean APIs for managing user pools and authentication flows.
Home-page: https://github.com/nerdmonkey/python-sanctum
License: MIT
Keywords: aws,cognito,authentication,rbac,jwt,user-management
Author: Sydel Palinlin
Author-email: sydel.palinlin@gmail.com
Requires-Python: >=3.8,<4.0
Classifier: Development Status :: 4 - Beta
Classifier: Intended Audience :: Developers
Classifier: License :: OSI Approved :: MIT License
Classifier: Operating System :: OS Independent
Classifier: Programming Language :: Python :: 3
Classifier: Programming Language :: Python :: 3.8
Classifier: Programming Language :: Python :: 3.9
Classifier: Programming Language :: Python :: 3.10
Classifier: Programming Language :: Python :: 3.11
Classifier: Programming Language :: Python :: 3.12
Classifier: Programming Language :: Python :: 3.13
Classifier: Topic :: Internet :: WWW/HTTP
Classifier: Topic :: Security
Classifier: Topic :: Software Development :: Libraries :: Python Modules
Requires-Dist: PyJWT (>=2.8.0,<3.0.0)
Requires-Dist: boto3 (>=1.34.0,<2.0.0)
Requires-Dist: botocore (>=1.34.0,<2.0.0)
Project-URL: Documentation, https://github.com/nerdmonkey/python-sanctum/tree/main/docs
Project-URL: Repository, https://github.com/nerdmonkey/python-sanctum
